socytinet/__init__.py
socytinet-0.0.1.dev0.dist-info/METADATA
socytinet-0.0.1.dev0.dist-info/WHEEL
socytinet-0.0.1.dev0.dist-info/RECORD
